watchgraf-0.0.1.dist-info/METADATA
watchgraf-0.0.1.dist-info/WHEEL
watchgraf-0.0.1.dist-info/entry_points.txt
watchgraf/_watchgrafrs.pyi
watchgraf/__init__.py
watchgraf/types.py
watchgraf/cli.py
watchgraf/utils.py
watchgraf/py.typed
watchgraf/watcher.py
watchgraf/_watchgrafrs.abi3.so
watchgraf-0.0.1.dist-info/RECORD
