Metadata-Version: 2.1
Name: watchgraf
Version: 0.0.1
Requires-Dist: pytest~=7.1.3; extra == 'tests'
Requires-Dist: pytest-mock~=3.8.2; extra == 'tests'
Requires-Dist: pytest-cov~=3.0.0; extra == 'tests'
Provides-Extra: tests
Summary: Toy-like and fast files watching and code reload. Built with love from python and rust
Author-email: Nichita Morcotilo <nmorkotilo@gmail.com>
Requires-Python: >=3.9
